ans_pycli/__init__.py
ans_pycli/cli.py
ans_pycli/commands/BaseCommand.py
ans_pycli/commands/Command.py
ans_pycli/commands/Dev/DevCommmand.py
ans_pycli/commands/Dev/__init__.py
ans_pycli/commands/Dev/stubs/Cli.jinja
ans_pycli/commands/Dev/stubs/Command.jinja
ans_pycli/commands/__init__.py
ans_pycli/commands/mixins.py
ans_pycli/helpers.py
ans_pycli-0.0.5.dist-info/METADATA
ans_pycli-0.0.5.dist-info/entry_points.txt
ans_pycli-0.0.5.dist-info/WHEEL
ans_pycli-0.0.5.dist-info/RECORD
